rtl/core/defines.v

`define XLEN 32
`define INSTR_WIDTH 32
`define REG_IDX_WIDTH 5
`define PC_WIDTH 32

rtl/core/fetch_mini_dec.v

// 取指单元 简单译码
module fetch_mini_dec(
    input [`INSTR_WIDTH-1:0]    instr_i,
    output                      dec_bjp_o, // branch and jump
    output                      dec_bxx_o,
    output                      dec_jal_o,
    output                      dec_jalr_o,
    output [`REG_IDX_WIDTH-1:0] dec_jalr_rs1_idx_o,
    output [`XLEN-1:0]          dec_bjp_imm_o
);

    wire [6:0] opcode = instr_i[6:0];
   
    assign dec_bxx_o  = (opcode == 7'b1100011);
    assign dec_jal_o  = (opcode == 7'b1101111);
    assign dec_jalr_o = (opcode == 7'b1100111);
    
    assign dec_bjp_o = dec_bxx_o | dec_jal_o | dec_jal_o;

    assign dec_jalr_rs1_idx_o = instr_i[19:15];

    // imm 符号扩展到XLEN位
    // bxx和jal需要将立即数左移一位
    wire [`XLEN-1:0] bjp_imm_bxx  = { {19{instr_i[31]}}, instr_i[31], instr_i[7],     instr_i[30:25], instr_i[11:8],  1'b0 };
    wire [`XLEN-1:0] bjp_imm_jal  = { {11{instr_i[31]}}, instr_i[31],   instr_i[19:12], instr_i[20],    instr_i[30:21], 1'b0};
    wire [`XLEN-1:0] bjp_imm_jalr = { {20{instr_i[31]}}, instr_i[31:20]};

    // 并行多路选择器
    assign dec_bjp_imm_o = ({`XLEN{dec_bxx_o}}  & bjp_imm_bxx) 
                         | ({`XLEN{dec_jal_o}}  & bjp_imm_jal)
                         | ({`XLEN{dec_jalr_o}} & bjp_imm_jalr);

endmodule

rtl/core/instr_fetch.v

//xxxxxxxxxxxxxxxxxxxxxxxxxxxxxxxxxxxxxxxxxxxxxxxx//
// INSTRUCTION FETCH
//xxxxxxxxxxxxxxxxxxxxxxxxxxxxxxxxxxxxxxxxxxxxxxxx//

// 1. 对取回的指令进行简单译码
// 2. 简单的分支预测
// 3. PC生成
// 4. 根据PC访问ITCM/BUI

`include "defines.v"

module instr_fetch(
    // PC REG
    input  [`PC_WIDTH-1:0]    pc_i,
    output [`PC_WIDTH-1:0]    if_pc_next_o,
    
    // IF_ID REG
    output [`INSTR_WIDTH-1:0] if_instr_o,
    output [`PC_WIDTH-1:0]    if_pc_o
);

    reg [`INSTR_WIDTH-1:0] instr;

//xxxxxxxxxxxxxxxxxxxxxxxxxxxxxxxxxxxxxxxxxxxxxxxx//
// 部分译码
// 用于分支预测          
//xxxxxxxxxxxxxxxxxxxxxxxxxxxxxxxxxxxxxxxxxxxxxxxx//
    
    wire dec_bjp;
    wire dec_bxx;
    wire dec_jal;
    wire dec_jalr;
    wire [`REG_IDX_WIDTH-1:0] dec_jalr_rs1_idx;
    wire [`XLEN-1:0] dec_bjp_imm;

    fetch_mini_dec fmd_1(
        .instr_i            (instr),
        .dec_bjp_o          (dec_bjp),
        .dec_bxx_o          (dec_bxx),
        .dec_jal_o          (dec_jal),
        .dec_jalr_o         (dec_jalr),
        .dec_jalr_rs1_idx_o (dec_jalr_rs1_idx),
        .dec_bjp_imm_o      (dec_bjp_imm)
    );

//xxxxxxxxxxxxxxxxxxxxxxxxxxxxxxxxxxxxxxxxxxxxxxxx//
//  分支预测
//xxxxxxxxxxxxxxxxxxxxxxxxxxxxxxxxxxxxxxxxxxxxxxxx//

    // 1. jal and jalr 直接跳转
    // 2. bxx 向后预测为跳转
    wire prdt_taken = ((dec_jal | dec_jalr) | (dec_bxx & dec_bjp_imm[31]));
   
    wire jalr_rs1_x0 = (dec_jalr_rs1_idx == `REG_IDX_WIDTH'd0);
    wire jalr_rs1_x1 = (dec_jalr_rs1_idx == `REG_IDX_WIDTH'd1);

    reg [`XLEN-1:0] prdt_pc_add_op1;
    
    always @(*) begin
        if(dec_jalr) begin // jalr
            if(jalr_rs1_x0) 
                prdt_pc_add_op1 = `XLEN'd0;
            else if(jalr_rs1_x1)
                prdt_pc_add_op1 = `XLEN'd1;
            else
                prdt_pc_add_op1 = `XLEN'd2;
        end else begin // jal && bxx
            prdt_pc_add_op1 = pc_i;
        end
    end
    
    wire [`XLEN-1:0] prdt_pc_add_op2 = dec_bjp_imm;

//xxxxxxxxxxxxxxxxxxxxxxxxxxxxxxxxxxxxxxxxxxxxxxxx//
//  PC生成 产生下一周期的PC
//xxxxxxxxxxxxxxxxxxxxxxxxxxxxxxxxxxxxxxxxxxxxxxxx//
    
    
    reg [`PC_WIDTH-1:0] pc_add_op1;
    reg [`PC_WIDTH-1:0] pc_add_op2;
    
    always @(*) begin
        if(dec_bjp & prdt_taken) // 预测跳转
            pc_add_op1 = prdt_pc_add_op1;
        else
            pc_add_op1 = pc_i;
    end

    always @(*) begin
        if(dec_bjp & prdt_taken) // 预测跳转
            pc_add_op2 = prdt_pc_add_op2;
        else
            pc_add_op2 = `PC_WIDTH'd4;
    end

    // 下一条PC
    assign if_pc_next_o = pc_add_op1 + pc_add_op2;


endmodule

rtl/core/pc_reg.v
`include "defines.v"

module pc_reg(
    input                  clk,
    input                  rst_n,
    input  [`PC_WIDTH-1:0] pc_next_i,
    input                  stall_i,
    output [`PC_WIDTH-1:0] pc_o
);

    reg [`PC_WIDTH-1:0] pc_r;

    always @(posedge clk or negedge rst_n) begin
        if(~rst_n) // 复位
            pc_r <= `PC_WIDTH'b0;
        else if(stall_i) // 暂停信号
            pc_r <= pc_r;
        else
            pc_r <= pc_next_i;
    end

    assign pc_o = pc_r;

endmodule

rtl/core/riscx.v
`include "defines.v"

module riscx(
    input clk,
    input rst_n
);

    wire [`PC_WIDTH-1:0] if2pr_pc_next;
    wire [`PC_WIDTH-1:0] pr2if_pc;

    wire [`INSTR_WIDTH-1:0] if2if_id_reg_instr;
    wire [`PC_WIDTH-1:0] if2if_id_reg_pc;

//xxxxxxxxxxxxxxxxxxxxxxxxxxxxxxxxxxxxxxxxxxxxxxxx//
// 取指阶段     
//xxxxxxxxxxxxxxxxxxxxxxxxxxxxxxxxxxxxxxxxxxxxxxxx//

    pc_reg pru(
        .clk       (clk),
        .rst_n     (rst_n),
        .pc_next_i (if2pr_pc_next),
        .stall_i   (1'b0),
        .pc_o      (pr2if_pc)
    );

    instr_fetch ifu(
        .pc_i(pr2if_pc),
        .if_pc_next_o(if2pr_pc_next),
        .if_instr_o(if2if_id_reg_instr),
        .if_pc_o(if2if_id_reg_pc)
    );

endmodule

rtl/core/wave.vcd
$version Generated by VerilatedVcd $end
$date Sat Nov 26 12:12:48 2022 $end
$timescale 1ps $end

 $scope module TOP $end
  $var wire  1 + clk $end
  $var wire  1 , rst_n $end
  $scope module riscx $end
   $var wire  1 + clk $end
   $var wire 32 - if2if_id_reg_instr [31:0] $end
   $var wire 32 . if2if_id_reg_pc [31:0] $end
   $var wire 32 ' if2pr_pc_next [31:0] $end
   $var wire 32 ( pr2if_pc [31:0] $end
   $var wire  1 , rst_n $end
   $scope module ifu $end
    $var wire  1 # dec_bjp $end
    $var wire 32 $ dec_bjp_imm [31:0] $end
    $var wire  1 1 dec_bxx $end
    $var wire  1 2 dec_jal $end
    $var wire  1 3 dec_jalr $end
    $var wire  5 4 dec_jalr_rs1_idx [4:0] $end
    $var wire 32 - if_instr_o [31:0] $end
    $var wire 32 ' if_pc_next_o [31:0] $end
    $var wire 32 . if_pc_o [31:0] $end
    $var wire 32 0 instr [31:0] $end
    $var wire  1 5 jalr_rs1_x0 $end
    $var wire  1 6 jalr_rs1_x1 $end
    $var wire 32 * pc_add_op1 [31:0] $end
    $var wire 32 & pc_add_op2 [31:0] $end
    $var wire 32 ( pc_i [31:0] $end
    $var wire 32 ) prdt_pc_add_op1 [31:0] $end
    $var wire 32 $ prdt_pc_add_op2 [31:0] $end
    $var wire  1 % prdt_taken $end
    $scope module fmd_1 $end
     $var wire 32 8 bjp_imm_bxx [31:0] $end
     $var wire 32 9 bjp_imm_jal [31:0] $end
     $var wire 32 : bjp_imm_jalr [31:0] $end
     $var wire 32 $ dec_bjp_imm_o [31:0] $end
     $var wire  1 # dec_bjp_o $end
     $var wire  1 1 dec_bxx_o $end
     $var wire  1 2 dec_jal_o $end
     $var wire  1 3 dec_jalr_o $end
     $var wire  5 4 dec_jalr_rs1_idx_o [4:0] $end
     $var wire 32 0 instr_i [31:0] $end
     $var wire  7 7 opcode [6:0] $end
    $upscope $end
   $upscope $end
   $scope module pru $end
    $var wire  1 + clk $end
    $var wire 32 ' pc_next_i [31:0] $end
    $var wire 32 ( pc_o [31:0] $end
    $var wire 32 ( pc_r [31:0] $end
    $var wire  1 , rst_n $end
    $var wire  1 / stall_i $end
   $upscope $end
  $upscope $end
 $upscope $end
$enddefinitions $end


#0
0#
b00000000000000000000000000000000 $
0%
b00000000000000000000000000000100 &
b00000000000000000000000000000100 '
b00000000000000000000000000000000 (
b00000000000000000000000000000000 )
b00000000000000000000000000000000 *
1+
1,
b00000000000000000000000000000000 -
b00000000000000000000000000000000 .
0/
b00000000000000000000000000000000 0
01
02
03
b00000 4
15
06
b0000000 7
b00000000000000000000000000000000 8
b00000000000000000000000000000000 9
b00000000000000000000000000000000 :
#1
0+
#2
b00000000000000000000000000001000 '
b00000000000000000000000000000100 (
b00000000000000000000000000000100 )
b00000000000000000000000000000100 *
1+
#3
0+
#4
b00000000000000000000000000001100 '
b00000000000000000000000000001000 (
b00000000000000000000000000001000 )
b00000000000000000000000000001000 *
1+
#5
0+
#6
b00000000000000000000000000010000 '
b00000000000000000000000000001100 (
b00000000000000000000000000001100 )
b00000000000000000000000000001100 *
1+
#7
0+
#8
b00000000000000000000000000010100 '
b00000000000000000000000000010000 (
b00000000000000000000000000010000 )
b00000000000000000000000000010000 *
1+
#9
0+
#10
b00000000000000000000000000011000 '
b00000000000000000000000000010100 (
b00000000000000000000000000010100 )
b00000000000000000000000000010100 *
1+
#11
0+
#12
b00000000000000000000000000011100 '
b00000000000000000000000000011000 (
b00000000000000000000000000011000 )
b00000000000000000000000000011000 *
1+
#13
0+
#14
b00000000000000000000000000100000 '
b00000000000000000000000000011100 (
b00000000000000000000000000011100 )
b00000000000000000000000000011100 *
1+
#15
0+
#16
b00000000000000000000000000100100 '
b00000000000000000000000000100000 (
b00000000000000000000000000100000 )
b00000000000000000000000000100000 *
1+
#17
0+
#18
b00000000000000000000000000101000 '
b00000000000000000000000000100100 (
b00000000000000000000000000100100 )
b00000000000000000000000000100100 *
1+
